ClusterShell/Communication.py
ClusterShell/Defaults.py
ClusterShell/Event.py
ClusterShell/Gateway.py
ClusterShell/MsgTree.py
ClusterShell/NodeSet.py
ClusterShell/NodeUtils.py
ClusterShell/Propagation.py
ClusterShell/RangeSet.py
ClusterShell/Task.py
ClusterShell/Topology.py
ClusterShell/__init__.py
ClusterShell/CLI/Clubak.py
ClusterShell/CLI/Clush.py
ClusterShell/CLI/Config.py
ClusterShell/CLI/Display.py
ClusterShell/CLI/Error.py
ClusterShell/CLI/Nodeset.py
ClusterShell/CLI/OptionParser.py
ClusterShell/CLI/Utils.py
ClusterShell/CLI/__init__.py
ClusterShell/CLI/__pycache__/Clubak.cpython-36.opt-1.pyc
ClusterShell/CLI/__pycache__/Clush.cpython-36.opt-1.pyc
ClusterShell/CLI/__pycache__/Config.cpython-36.opt-1.pyc
ClusterShell/CLI/__pycache__/Display.cpython-36.opt-1.pyc
ClusterShell/CLI/__pycache__/Error.cpython-36.opt-1.pyc
ClusterShell/CLI/__pycache__/Nodeset.cpython-36.opt-1.pyc
ClusterShell/CLI/__pycache__/OptionParser.cpython-36.opt-1.pyc
ClusterShell/CLI/__pycache__/Utils.cpython-36.opt-1.pyc
ClusterShell/CLI/__pycache__/__init__.cpython-36.opt-1.pyc
ClusterShell/Engine/EPoll.py
ClusterShell/Engine/Engine.py
ClusterShell/Engine/Factory.py
ClusterShell/Engine/Poll.py
ClusterShell/Engine/Select.py
ClusterShell/Engine/__init__.py
ClusterShell/Engine/__pycache__/EPoll.cpython-36.opt-1.pyc
ClusterShell/Engine/__pycache__/Engine.cpython-36.opt-1.pyc
ClusterShell/Engine/__pycache__/Factory.cpython-36.opt-1.pyc
ClusterShell/Engine/__pycache__/Poll.cpython-36.opt-1.pyc
ClusterShell/Engine/__pycache__/Select.cpython-36.opt-1.pyc
ClusterShell/Engine/__pycache__/__init__.cpython-36.opt-1.pyc
ClusterShell/Worker/EngineClient.py
ClusterShell/Worker/Exec.py
ClusterShell/Worker/Pdsh.py
ClusterShell/Worker/Popen.py
ClusterShell/Worker/Rsh.py
ClusterShell/Worker/Ssh.py
ClusterShell/Worker/Tree.py
ClusterShell/Worker/Worker.py
ClusterShell/Worker/__init__.py
ClusterShell/Worker/fastsubprocess.py
ClusterShell/Worker/__pycache__/EngineClient.cpython-36.opt-1.pyc
ClusterShell-1.8.3.dist-info/COPYING.LGPLv2.1
ClusterShell-1.8.3.dist-info/METADATA
ClusterShell-1.8.3.dist-info/WHEEL
ClusterShell-1.8.3.dist-info/entry_points.txt
ClusterShell-1.8.3.dist-info/top_level.txt
ClusterShell-1.8.3.dist-info/RECORD
