Metadata-Version: 2.1
Name: ClusterShell
Version: 1.8.3
Summary: ClusterShell library and tools
Home-page: http://clustershell.sourceforge.net/
Author: Stephane Thiell
Author-email: sthiell@stanford.edu
License: LGPLv2+
Download-URL: http://sourceforge.net/projects/clustershell/files/clustershell/1.8.3/
Keywords: clustershell,clush,clubak,nodeset
Platform: GNU/Linux
Platform: BSD
Platform: MacOSX
Classifier: Development Status :: 5 - Production/Stable
Classifier: Environment :: Console
Classifier: Intended Audience :: System Administrators
Classifier: License :: OSI Approved :: GNU Lesser General Public License v2 or later (LGPLv2+)
Classifier: Operating System :: MacOS :: MacOS X
Classifier: Operating System :: POSIX :: BSD
Classifier: Operating System :: POSIX :: Linux
Classifier: Programming Language :: Python
Classifier: Programming Language :: Python :: 2.6
Classifier: Programming Language :: Python :: 2.7
Classifier: Programming Language :: Python :: 3
Classifier: Topic :: Software Development :: Libraries :: Python Modules
Classifier: Topic :: System :: Clustering
Classifier: Topic :: System :: Distributed Computing
Requires-Dist: PyYAML
